bloomfpy/__init__.py
bloomfpy/bloomfpy.py
bloomfpy-1.1.0.dist-info/LICENSE.txt
bloomfpy-1.1.0.dist-info/METADATA
bloomfpy-1.1.0.dist-info/WHEEL
bloomfpy-1.1.0.dist-info/top_level.txt
bloomfpy-1.1.0.dist-info/zip-safe
bloomfpy-1.1.0.dist-info/RECORD
